MANIFEST.in
README.rst
setup.py
mathexpressions/__init__.py
mathexpressions/lib.py
mathexpressions.egg-info/PKG-INFO
mathexpressions.egg-info/SOURCES.txt
mathexpressions.egg-info/dependency_links.txt
mathexpressions.egg-info/not-zip-safe
mathexpressions.egg-info/top_level.txt