Metadata-Version: 1.1
Name: mathexpressions
Version: 1.0.0
Summary: Python library for parsing and solving math expressions. Example Usage: https://github.com/NoahPeeters/pymathexpressions/blob/master/example.py Documentation is coming soon.
Home-page: https://github.com/NoahPeeters/pymathexpressions
Author: Noah Peeters
Author-email: noah.peeters@icloud.com
License: MIT
Platform: UNKNOWN
Classifier: Development Status :: 4 - Beta
Classifier: License :: OSI Approved :: MIT License
Classifier: Programming Language :: Python :: 3
Classifier: License :: OSI Approved :: MIT License
Classifier: Programming Language :: Python
Classifier: Topic :: Text Processing :: Linguistic
Classifier: Topic :: Scientific/Engineering :: Mathematics
